eeauth/__init__.py
eeauth/api.py
eeauth/cli.py
eeauth/exceptions.py
eeauth/user_registry.py
eeauth-0.1.2.dist-info/METADATA
eeauth-0.1.2.dist-info/WHEEL
eeauth-0.1.2.dist-info/entry_points.txt
eeauth-0.1.2.dist-info/licenses/LICENSE
eeauth-0.1.2.dist-info/RECORD
