Metadata-Version: 2.1
Name: eeauth
Version: 0.1.2
Summary: An Earth Engine account manager.
Project-URL: Homepage, https://github.com/aazuspan/eeauth
Author: Aaron Zuspan
License: MIT License
License-File: LICENSE
Keywords: earthengine,gee,jupyter,notebook
Requires-Python: >=3.9
Requires-Dist: click
Requires-Dist: earthengine-api>=0.1.317
Requires-Dist: pydantic==2.*
